thermohi_hikari/__init__.py
thermohi_hikari/datalistio.py
thermohi_hikari/plotting.py
thermohi_hikari/thermoanalysis.py
thermohi_hikari-0.1.2.dist-info/METADATA
thermohi_hikari-0.1.2.dist-info/WHEEL
thermohi_hikari-0.1.2.dist-info/top_level.txt
thermohi_hikari-0.1.2.dist-info/RECORD
