Metadata-Version: 2.4
Name: thermohi-hikari
Version: 0.1.2
Summary: A thermogravimetric analysis helper tool by Hikari.
Home-page: https://github.com/QuicklimeHikari/thermohi
Author: Hikari Quicklime
License: MIT
Requires-Python: >=3.9
Dynamic: home-page
Dynamic: requires-python
